[
  {
    "student_name": "kiki",
    "dob": "02/03/2004",
    "gender": "Female",
    "aadhar_number": "1234-5678-9812",
    "blood_group": "",
    "nationality": "Indian",
    "religion": "",
    "caste": "",
    "class_applying": "LKG",
    "school": "SBOA Annanagar",
    "medium": "English",
    "distance_km": 5.0,
    "address": "Jayalakshmi blocks, radha nagar, chromepet",
    "father_name": "Velu",
    "father_occupation": "",
    "father_phone": "7904975769",
    "mother_name": "Uma",
    "mother_occupation": "",
    "mother_phone": "",
    "email": "krithikav234@gmail.com",
    "annual_income": "",
    "guardian_name": "",
    "guardian_phone": "",
    "prev_school": "",
    "prev_class": "",
    "percentage": 0.0,
    "tc_number": "",
    "leaving_date": "",
    "grade": "",
    "has_sibling": false,
    "sibling_name": "",
    "sibling_class": "",
    "is_ews": false,
    "is_staff_child": false,
    "is_rte": false,
    "achievements": "",
    "medical_info": "",
    "status": "Pending",
    "score": 0,
    "phone": "7904975769",
    "_id": "9feb7c48",
    "created_at": "2026-05-03T18:15:27.737603"
  },
  {
    "student_name": "Mahadev M Lithan",
    "father_name": "Lithan MR",
    "email": "neethulithan465@gmail.com",
    "class_applying": "LKG",
    "father_phone": "9995467465",
    "mother_phone": "9995244408",
    "dob": "03/06/2020",
    "gender": "Female",
    "address": "Mothirappillil House Kedamangalam North Paravoor CHENNAI 683513",
    "message": "Currently studying in Prekg SBOA. ",
    "counsellor_remarks": "REGISTERED ",
    "next_followup": "",
    "submitted_at": "18/01/2026",
    "phone": "9995467465",
    "school": "SBOA Annanagar",
    "status": "Pending",
    "score": 0,
    "source": "excel_import",
    "_id": "c27d24ff",
    "created_at": "2026-05-03T18:27:27.878262"
  },
  {
    "student_name": "Deza Maria Antony",
    "father_name": "Antony Francis M R",
    "email": "antonyfrancismr@gmail.com",
    "class_applying": "LKG",
    "father_phone": "7994711201",
    "mother_phone": "8921096499",
    "dob": "29/07/2021",
    "gender": "Male",
    "address": "Mathirappilly House, Edayakunnam, south chittoor p o ,Cochin 682027",
    "message": "Siblings of Deon Antony(std 7 A) and Deric Antony (std 3 A) ",
    "counsellor_remarks": "REGISTERED",
    "next_followup": "",
    "submitted_at": "19/01/2026",
    "phone": "7994711201",
    "school": "SBOA Annanagar",
    "status": "Pending",
    "score": 0,
    "source": "excel_import",
    "_id": "b3915f4d",
    "created_at": "2026-05-03T18:27:27.910543"
  },
  {
    "student_name": "Avyaan Sajit Kurup ",
    "father_name": "Sajit Balakrishnan Kurup ",
    "email": "kurup.sajit@gmail.com",
    "class_applying": "Pre-KG",
    "father_phone": "8169431775",
    "mother_phone": "7798319206",
    "dob": "23/08/2022",
    "gender": "Female",
    "address": "205 D, SAEYAS, EDAYAKUNNAM CAPELA, CHEMNALLOR, CHERANALLOR CHENNAI, 632034",
    "message": "",
    "counsellor_remarks": "REGISTERED IN SCHOOL WEBSITE ON 27/1/26",
    "next_followup": "",
    "submitted_at": "23/01/2026",
    "phone": "8169431775",
    "school": "SBOA Annanagar",
    "status": "Pending",
    "score": 0,
    "source": "excel_import",
    "_id": "4c9c2549",
    "created_at": "2026-05-03T18:27:27.936882"
  },
  {
    "student_name": "Ananya Sajit Kurup ",
    "father_name": "Sajit Balakrishnan Kurup ",
    "email": "kurup.sajit@gmail.com",
    "class_applying": "Class 7",
    "father_phone": "8169431775",
    "mother_phone": "7798319206",
    "dob": "02/09/2014",
    "gender": "Male",
    "address": "205 D, SAEYAS, EDAYAKUNNAM CAPELA, CHEMNALLOR, CHERANALLOR CHENNAI, 632034",
    "message": "",
    "counsellor_remarks": "REGISTERED",
    "next_followup": "",
    "submitted_at": "23/01/2026",
    "phone": "8169431775",
    "school": "SBOA Annanagar",
    "status": "Pending",
    "score": 0,
    "source": "excel_import",
    "_id": "708fcfed",
    "created_at": "2026-05-03T18:27:27.963645"
  },
  {
    "student_name": "Jehan Pherozeshah Rayomand",
    "father_name": "kunjiandi Rayomand ",
    "email": "vellakaarathakundi@gmail.com",
    "class_applying": "Pre-KG",
    "father_phone": "112",
    "mother_phone": "112",
    "dob": "31/12/1950",
    "gender": "Male",
    "address": "south chitoor next to tamil nadu",
    "message": "hi i am koolo want sboa want to become abhinav menon",
    "counsellor_remarks": "fake message.No contact number ",
    "next_followup": "",
    "submitted_at": "24/01/2026",
    "phone": "112",
    "school": "SBOA Annanagar",
    "status": "Pending",
    "score": 0,
    "source": "excel_import",
    "_id": "9b10007b",
    "created_at": "2026-05-03T18:27:27.991035"
  },
  {
    "student_name": "ADWAITH.A",
    "father_name": "ANISH KUMAR",
    "email": "anishkumar111@gmail.com",
    "class_applying": "Class 11",
    "father_phone": "9562007070",
    "mother_phone": "9074859231",
    "dob": "26/11/2010",
    "gender": "Female",
    "address": "KAILASAM HOUSE, OPP BLOCK PANCHAYATH OFFICE, KAITHARAM, NORTH PARAVOOR",
    "message": "",
    "counsellor_remarks": "REGISTERED FOR BIO MATHS",
    "next_followup": "",
    "submitted_at": "26/01/2026",
    "phone": "9562007070",
    "school": "SBOA Annanagar",
    "status": "Pending",
    "score": 0,
    "source": "excel_import",
    "_id": "22ac3c0e",
    "created_at": "2026-05-03T18:27:28.021979"
  },
  {
    "student_name": "Baby Augustine K.X",
    "father_name": "Praveen Xavier K.A",
    "email": "praveenxavier388@gmail.com",
    "class_applying": "LKG",
    "father_phone": "7560936652",
    "mother_phone": "7356212367",
    "dob": "17/11/2021",
    "gender": "Male",
    "address": "Komaranchath house, boat jetty road,vaduthala p.o",
    "message": "For new admission",
    "counsellor_remarks": "ADMISSION TAKEN",
    "next_followup": "",
    "submitted_at": "27/01/2026",
    "phone": "7560936652",
    "school": "SBOA Annanagar",
    "status": "Pending",
    "score": 0,
    "source": "excel_import",
    "_id": "e8bac502",
    "created_at": "2026-05-03T18:27:28.056065"
  },
  {
    "student_name": "Neerav Anil",
    "father_name": "Anil Kumar Nelluvelil Sukumaran",
    "email": "PREETHIKV09@gmail.com",
    "class_applying": "LKG",
    "father_phone": "7356421309",
    "mother_phone": "",
    "dob": "05/09/2019",
    "gender": "Female",
    "address": "Nelluvelil House, South chittoor pin:682027",
    "message": "New admission ",
    "counsellor_remarks": "ADMISSION TAKEN",
    "next_followup": "",
    "submitted_at": "28/01/2026",
    "phone": "7356421309",
    "school": "SBOA Annanagar",
    "status": "Pending",
    "score": 0,
    "source": "excel_import",
    "_id": "a913f5ac",
    "created_at": "2026-05-03T18:27:28.086661"
  },
  {
    "student_name": "Eva Elza Varghese",
    "father_name": "Father",
    "email": "vjomy99@gmail.com",
    "class_applying": "LKG",
    "father_phone": "9400646270",
    "mother_phone": "",
    "dob": "30/06/2022",
    "gender": "Male",
    "address": "Chettakulathinkara kodanad Perumbavoor CHENNAI pin 683544",
    "message": "",
    "counsellor_remarks": "Message repeated",
    "next_followup": "",
    "submitted_at": "29/01/2026",
    "phone": "9400646270",
    "school": "SBOA Annanagar",
    "status": "Pending",
    "score": 0,
    "source": "excel_import",
    "_id": "ef2b7b85",
    "created_at": "2026-05-03T18:27:28.112568"
  },
  {
    "student_name": "PADMESH SHENOY E P",
    "father_name": "PRAFUL E P",
    "email": "prafulepleo@gmail.com",
    "class_applying": "LKG",
    "father_phone": "9495016586",
    "mother_phone": "9946290014",
    "dob": "19/03/2022",
    "gender": "Female",
    "address": "EDAVAZHIKKAL HOUSE THUNDATHUMKADAVU VARAPUZHA P O CHENNAI KERALA- 683517",
    "message": "Seeking admission for Padmesh to LKG",
    "counsellor_remarks": "SURE ADMISSION",
    "next_followup": "",
    "submitted_at": "01/02/2026",
    "phone": "9495016586",
    "school": "SBOA Annanagar",
    "status": "Pending",
    "score": 0,
    "source": "excel_import",
    "_id": "d303de1b",
    "created_at": "2026-05-03T18:27:28.150501"
  },
  {
    "student_name": "Bhavath Vishnu ",
    "father_name": "Vishnu Mohan ",
    "email": "advakhilakv2020@gmail.com",
    "class_applying": "Class 1",
    "father_phone": "7012916717",
    "mother_phone": "9061599505",
    "dob": "30/07/2019",
    "gender": "Male",
    "address": "Govindam, Kodolipram, P.O. Pattannur, Kannur, 670595",
    "message": "",
    "counsellor_remarks": "REGISTERED. will Visit school this week",
    "next_followup": "",
    "submitted_at": "08/02/2026",
    "phone": "7012916717",
    "school": "SBOA Annanagar",
    "status": "Pending",
    "score": 0,
    "source": "excel_import",
    "_id": "bae286dc",
    "created_at": "2026-05-03T18:27:28.179746"
  },
  {
    "student_name": "Valentina Armstrong Valath",
    "father_name": "Josephine Roshna Pinheiro",
    "email": "valath.mailbox@gmail.com",
    "class_applying": "Pre-KG",
    "father_phone": "8669439463",
    "mother_phone": "8089318922",
    "dob": "26/05/2023",
    "gender": "Male",
    "address": "Vadakke valath House vvk valath road south chittoor po kochi 682027",
    "message": "",
    "counsellor_remarks": "NO RESPONSE ",
    "next_followup": "",
    "submitted_at": "08/02/2026",
    "phone": "8669439463",
    "school": "SBOA Annanagar",
    "status": "Pending",
    "score": 0,
    "source": "excel_import",
    "_id": "0316428a",
    "created_at": "2026-05-03T18:27:28.203237"
  },
  {
    "student_name": "Hayan Cino ",
    "father_name": "Cino Varghese ",
    "email": "cinochennattu@gmail.com",
    "class_applying": "LKG",
    "father_phone": "9745672247",
    "mother_phone": "6282314402",
    "dob": "13/01/2022",
    "gender": "Male",
    "address": "Chennattu ",
    "message": "",
    "counsellor_remarks": "ADMISSION TAKEN",
    "next_followup": "",
    "submitted_at": "13/02/2026",
    "phone": "9745672247",
    "school": "SBOA Annanagar",
    "status": "Pending",
    "score": 0,
    "source": "excel_import",
    "_id": "fb1e6699",
    "created_at": "2026-05-03T18:27:28.229691"
  },
  {
    "student_name": "Arhaan Sidharth",
    "father_name": "Sidharth S",
    "email": "madhurismenon16@gmail.com",
    "class_applying": "Pre-KG",
    "father_phone": "9567650210",
    "mother_phone": "7559957547",
    "dob": "11/02/2023",
    "gender": "Male",
    "address": "B-102, Dreamflower Begonia,  Vidya Nagar, Kadavanthra ",
    "message": "Admission enquiry for Pre-KG",
    "counsellor_remarks": "Took admission in another school ",
    "next_followup": "",
    "submitted_at": "15/02/2026",
    "phone": "9567650210",
    "school": "SBOA Annanagar",
    "status": "Pending",
    "score": 0,
    "source": "excel_import",
    "_id": "1bb8773f",
    "created_at": "2026-05-03T18:27:28.258336"
  },
  {
    "student_name": "INIYAN GANESH",
    "father_name": "Ganesh",
    "email": "poornimae5@gmail.com",
    "class_applying": "Class 1",
    "father_phone": "9940448233",
    "mother_phone": "9789071603",
    "dob": "04/03/2020",
    "gender": "Male",
    "address": "KVRA 16, Kavshikam, kaloor, CHENNAI - 682017",
    "message": "Hi.. we are seeking admission for first grade",
    "counsellor_remarks": "ADMISSION TAKEN",
    "next_followup": "",
    "submitted_at": "19/02/2026",
    "phone": "9940448233",
    "school": "SBOA Annanagar",
    "status": "Pending",
    "score": 0,
    "source": "excel_import",
    "_id": "200bfe0d",
    "created_at": "2026-05-03T18:27:28.293158"
  },
  {
    "student_name": "Raechel Geo Antony",
    "father_name": "Shalett Joseph",
    "email": "shalett2015@gmail.com",
    "class_applying": "Class 1",
    "father_phone": "7034995012",
    "mother_phone": "7034995012",
    "dob": "06/04/2019",
    "gender": "Male",
    "address": "Falt No B2, VB Court, LFC Road, Kaloor, 682017",
    "message": "I would like to know more about the admission procedures of the school",
    "counsellor_remarks": "ADMISSION TAKEN ",
    "next_followup": "",
    "submitted_at": "20/02/2026",
    "phone": "7034995012",
    "school": "SBOA Annanagar",
    "status": "Pending",
    "score": 0,
    "source": "excel_import",
    "_id": "b9413d1f",
    "created_at": "2026-05-03T18:27:28.325825"
  },
  {
    "student_name": "Keyaan",
    "father_name": "Akbersha",
    "email": "Akbersha0001@gmail.com",
    "class_applying": "LKG",
    "father_phone": "8050861886",
    "mother_phone": "9108985567",
    "dob": "04/04/2022",
    "gender": "Male",
    "address": "National signature Cheranellor ",
    "message": "I would like to know in details about admission my son for LKG",
    "counsellor_remarks": "ADMISSION TAKEN ",
    "next_followup": "",
    "submitted_at": "20/02/2026",
    "phone": "8050861886",
    "school": "SBOA Annanagar",
    "status": "Pending",
    "score": 0,
    "source": "excel_import",
    "_id": "48490201",
    "created_at": "2026-05-03T18:27:28.357544"
  },
  {
    "student_name": "Bharath Pradeep Pillai ",
    "father_name": "Mrudula omanakuttan ",
    "email": "mridulaokuttan22@gmail.com",
    "class_applying": "Class 11",
    "father_phone": "8156842476",
    "mother_phone": "8156842476",
    "dob": "06/05/2010",
    "gender": "Male",
    "address": "Thittazhathu thiruvonam house,kaitharam po,cheriyappilly,pin 683519",
    "message": "",
    "counsellor_remarks": "REGISTERED ",
    "next_followup": "",
    "submitted_at": "22/02/2026",
    "phone": "8156842476",
    "school": "SBOA Annanagar",
    "status": "Pending",
    "score": 0,
    "source": "excel_import",
    "_id": "4bd551b9",
    "created_at": "2026-05-03T18:27:28.394814"
  },
  {
    "student_name": "Iza Elana Prince ",
    "father_name": "Hilda Maria Tennison ",
    "email": "hildamariatennison3@gmail.com",
    "class_applying": "LKG",
    "father_phone": "9061812907",
    "mother_phone": "9495253900",
    "dob": "05/06/2021",
    "gender": "Male",
    "address": "Elegant palace house , sree narayana cross road, karukappilly, kaloor",
    "message": "",
    "counsellor_remarks": "Enquiry already exist in Lead tracker ",
    "next_followup": "",
    "submitted_at": "24/02/2026",
    "phone": "9061812907",
    "school": "SBOA Annanagar",
    "status": "Pending",
    "score": 0,
    "source": "excel_import",
    "_id": "b8f578c9",
    "created_at": "2026-05-03T18:27:28.425426"
  },
  {
    "student_name": "Dua mariyam",
    "father_name": "Neethu saji",
    "email": "beahalmariyam@gmail.com",
    "class_applying": "UKG",
    "father_phone": "9778260184",
    "mother_phone": "9995096506",
    "dob": "14/08/2021",
    "gender": "Male",
    "address": "Elavunkal House puliyanmala po hiltop Idukki ",
    "message": "",
    "counsellor_remarks": "REGISTERED ",
    "next_followup": "",
    "submitted_at": "04/03/2026",
    "phone": "9778260184",
    "school": "SBOA Annanagar",
    "status": "Pending",
    "score": 0,
    "source": "excel_import",
    "_id": "d329b55e",
    "created_at": "2026-05-03T18:27:28.452431"
  },
  {
    "student_name": "Iswa Mariyam ",
    "father_name": "NEETHU SAJI ",
    "email": "beahalmariyam@gmail.com",
    "class_applying": "Class 1",
    "father_phone": "9778260184",
    "mother_phone": "9995096506",
    "dob": "29/11/2019",
    "gender": "Male",
    "address": "Elavunkal House puliyanmala po hiltop Idukki Kerala ",
    "message": "",
    "counsellor_remarks": "REGISTERED ",
    "next_followup": "",
    "submitted_at": "04/03/2026",
    "phone": "9778260184",
    "school": "SBOA Annanagar",
    "status": "Pending",
    "score": 0,
    "source": "excel_import",
    "_id": "3ae762c6",
    "created_at": "2026-05-03T18:27:28.480433"
  },
  {
    "student_name": "Mridul s Nair",
    "father_name": "Sarath v r ",
    "email": "vr.sarath9@gmail.com",
    "class_applying": "Class 1",
    "father_phone": "8330876804",
    "mother_phone": "",
    "dob": "26/06/2020",
    "gender": "Male",
    "address": "Krishna priya 91",
    "message": "",
    "counsellor_remarks": "Already exist in lead tracker ",
    "next_followup": "",
    "submitted_at": "05/03/2026",
    "phone": "8330876804",
    "school": "SBOA Annanagar",
    "status": "Pending",
    "score": 0,
    "source": "excel_import",
    "_id": "c92532fb",
    "created_at": "2026-05-03T18:27:28.506561"
  },
  {
    "student_name": "Rigved Tv",
    "father_name": "Vineeth TR",
    "email": "msinc1000@gmail.com",
    "class_applying": "Class 5",
    "father_phone": "9544236187",
    "mother_phone": "7907922508",
    "dob": "21/06/2016",
    "gender": "Male",
    "address": "Vaduthala ",
    "message": "",
    "counsellor_remarks": "REGISTERED ",
    "next_followup": "",
    "submitted_at": "05/03/2026",
    "phone": "9544236187",
    "school": "SBOA Annanagar",
    "status": "Pending",
    "score": 0,
    "source": "excel_import",
    "_id": "abfc1af6",
    "created_at": "2026-05-03T18:27:28.536894"
  },
  {
    "student_name": "Athvi Suraj",
    "father_name": "Suraj S",
    "email": "msinc1000@gmail.com",
    "class_applying": "UKG",
    "father_phone": "9995306587",
    "mother_phone": "8129680602",
    "dob": "13/04/2021",
    "gender": "Male",
    "address": "Devaswam thundi parambil Gopala prabhu road vochin-35",
    "message": "Admission for ukg 2026",
    "counsellor_remarks": "Contacted the parents and Registered link shared.They will register soon.",
    "next_followup": "13/3/25",
    "submitted_at": "06/03/2026",
    "phone": "9995306587",
    "school": "SBOA Annanagar",
    "status": "Pending",
    "score": 0,
    "source": "excel_import",
    "_id": "c6151cd9",
    "created_at": "2026-05-03T18:27:28.563403"
  },
  {
    "student_name": "Adhwaid K Pradeep ",
    "father_name": "KS Pradeep",
    "email": "msinc1000@gmail.com",
    "class_applying": "Class 11",
    "father_phone": "9947921509",
    "mother_phone": "9447796940",
    "dob": "07/09/2009",
    "gender": "Male",
    "address": "Korassery house,Vazhikkulangara,N.Paravur,pin 683513",
    "message": "Requesting admission for class 11th",
    "counsellor_remarks": "",
    "next_followup": "",
    "submitted_at": "10/03/2026",
    "phone": "9947921509",
    "school": "SBOA Annanagar",
    "status": "Pending",
    "score": 0,
    "source": "excel_import",
    "_id": "1ead7240",
    "created_at": "2026-05-03T18:27:28.590884"
  },
  {
    "student_name": "Yash Vinayak ",
    "father_name": "Nishanth ",
    "email": "msinc1000@gmail.com",
    "class_applying": "Class 11",
    "father_phone": "9947921510",
    "mother_phone": "9447796941",
    "dob": "23/09/2010",
    "gender": "Male",
    "address": "Kuruppassery house, varappuzha ",
    "message": "I would like to know about admission and also fee details ",
    "counsellor_remarks": "",
    "next_followup": "",
    "submitted_at": "10/03/2026",
    "phone": "9947921510",
    "school": "SBOA Annanagar",
    "status": "Pending",
    "score": 0,
    "source": "excel_import",
    "_id": "01a59cdd",
    "created_at": "2026-05-03T18:27:28.619485"
  },
  {
    "student_name": "Anvika Rahul",
    "father_name": "Rahul N K",
    "email": "msinc1000@gmail.com",
    "class_applying": "Class 1",
    "father_phone": "9947921511",
    "mother_phone": "9447796942",
    "dob": "10/10/2019",
    "gender": "Female",
    "address": "Alingal Parambil House Rubilane Thammanam",
    "message": "",
    "counsellor_remarks": "REGISTERED",
    "next_followup": "",
    "submitted_at": "11/03/2026",
    "phone": "9947921511",
    "school": "SBOA Annanagar",
    "status": "Pending",
    "score": 0,
    "source": "excel_import",
    "_id": "260ae3b4",
    "created_at": "2026-05-03T18:27:28.647078"
  },
  {
    "student_name": "Prithvi S Nath ",
    "father_name": "Sreenath N",
    "email": "msinc1000@gmail.com",
    "class_applying": "Class 1",
    "father_phone": "9947921512",
    "mother_phone": "9447796943",
    "dob": "07/03/2020",
    "gender": "Male",
    "address": "Pwra 8,Kumbalaparambil, Ponekara, meenchira road",
    "message": "Need to know details for standard 1 admission ",
    "counsellor_remarks": "REGISTERED",
    "next_followup": "",
    "submitted_at": "12/03/2026",
    "phone": "9947921512",
    "school": "SBOA Annanagar",
    "status": "Pending",
    "score": 0,
    "source": "excel_import",
    "_id": "67e7501e",
    "created_at": "2026-05-03T18:27:28.676538"
  },
  {
    "student_name": "Albinsten C N",
    "father_name": "Antony Nixon",
    "email": "msinc1000@gmail.com",
    "class_applying": "Class 11",
    "father_phone": "9947921513",
    "mother_phone": "9447796944",
    "dob": "24/12/2010",
    "gender": "Female",
    "address": "Cheevealil house , kothad",
    "message": "Admission for +1",
    "counsellor_remarks": "",
    "next_followup": "",
    "submitted_at": "12/03/2026",
    "phone": "9947921513",
    "school": "SBOA Annanagar",
    "status": "Pending",
    "score": 0,
    "source": "excel_import",
    "_id": "e6f44151",
    "created_at": "2026-05-03T18:27:28.705523"
  },
  {
    "student_name": "ABID ZAIN  P S",
    "father_name": "SHAMSUDHEEN P M",
    "email": "msinc1000@gmail.com",
    "class_applying": "Class 1",
    "father_phone": "9947921514",
    "mother_phone": "9447796945",
    "dob": "21/11/2019",
    "gender": "Female",
    "address": "POTHADY HOUSE PONNARIMANGALAM ,MULAVUKAD P O",
    "message": "I WANT TO KNOW ABOUT ADMISSION PROCEDURE FOR MY SON AND ALSO FEE STRUCTURE , VEHICLE SERVICE ,CLASS TIMING",
    "counsellor_remarks": "from moolampilly-all details  sent and admission link shared .After follow up NO RESPONSE ",
    "next_followup": "16/3/26",
    "submitted_at": "12/03/2026",
    "phone": "9947921514",
    "school": "SBOA Annanagar",
    "status": "Pending",
    "score": 0,
    "source": "excel_import",
    "_id": "45794ec2",
    "created_at": "2026-05-03T18:27:28.731716"
  },
  {
    "student_name": "Anamika Ajoob ",
    "father_name": "Ajoob K P",
    "email": "msinc1000@gmail.com",
    "class_applying": "Class 11",
    "father_phone": "9947921515",
    "mother_phone": "9447796946",
    "dob": "23/02/2010",
    "gender": "Female",
    "address": "Kandathithazham House, Mattummel Road, Cheranalloor ",
    "message": "",
    "counsellor_remarks": "REGISTERED",
    "next_followup": "",
    "submitted_at": "12/03/2026",
    "phone": "9947921515",
    "school": "SBOA Annanagar",
    "status": "Pending",
    "score": 0,
    "source": "excel_import",
    "_id": "f4f4e16b",
    "created_at": "2026-05-03T18:27:28.759684"
  },
  {
    "student_name": "Haridhev P Jiju ",
    "father_name": "P H Jiju",
    "email": "msinc1000@gmail.com",
    "class_applying": "Class 11",
    "father_phone": "9947921516",
    "mother_phone": "9447796947",
    "dob": "01/05/2010",
    "gender": "Female",
    "address": "4e, DD Silver Stone, Vaduthala ",
    "message": "Admission aloted?",
    "counsellor_remarks": "REGISTERED ",
    "next_followup": "",
    "submitted_at": "17/03/2026",
    "phone": "9947921516",
    "school": "SBOA Annanagar",
    "status": "Pending",
    "score": 0,
    "source": "excel_import",
    "_id": "24fa2655",
    "created_at": "2026-05-03T18:27:28.789332"
  },
  {
    "student_name": "Kalyani ER",
    "father_name": "BK Rammohan",
    "email": "msinc1000@gmail.com",
    "class_applying": "Class 11",
    "father_phone": "9947921517",
    "mother_phone": "9447796948",
    "dob": "03/06/2010",
    "gender": "Male",
    "address": "TATA Tritvam Apartments Tower 4 5B Goshree Pachalam link road CHENNAI-18",
    "message": "subjects-English, Physics ,Chemistry, Biology & Informatic Practices",
    "counsellor_remarks": "REGISTERED",
    "next_followup": "",
    "submitted_at": "20/03/2026",
    "phone": "9947921517",
    "school": "SBOA Annanagar",
    "status": "Pending",
    "score": 0,
    "source": "excel_import",
    "_id": "9c1b00ab",
    "created_at": "2026-05-03T18:27:28.819623"
  },
  {
    "student_name": "SANVIYA SS",
    "father_name": "SIVAPRASAD K",
    "email": "msinc1000@gmail.com",
    "class_applying": "Class 5",
    "father_phone": "9947921518",
    "mother_phone": "9447796949",
    "dob": "01/07/2016",
    "gender": "Female",
    "address": "SIVAKRIPA, ALAMKADAVU, KUTTIPALLAM POST, CHITTUR, PALAKKAD ",
    "message": "",
    "counsellor_remarks": "REGISTERED",
    "next_followup": "",
    "submitted_at": "22/03/2026",
    "phone": "9947921518",
    "school": "SBOA Annanagar",
    "status": "Pending",
    "score": 0,
    "source": "excel_import",
    "_id": "5afa6a2a",
    "created_at": "2026-05-03T18:27:28.853084"
  },
  {
    "student_name": "SIVANYA SS",
    "father_name": "SIVAPRASAD K",
    "email": "msinc1000@gmail.com",
    "class_applying": "Class 2",
    "father_phone": "9947921519",
    "mother_phone": "9447796950",
    "dob": "13/05/2019",
    "gender": "Female",
    "address": "SIVAKRIPA, ALAMKADAVU, KUTTIPALLAM POST, CHITTUR, PALAKKAD ",
    "message": "",
    "counsellor_remarks": "REGISTERED",
    "next_followup": "",
    "submitted_at": "22/03/2026",
    "phone": "9947921519",
    "school": "SBOA Annanagar",
    "status": "Pending",
    "score": 0,
    "source": "excel_import",
    "_id": "c35b2b27",
    "created_at": "2026-05-03T18:27:28.881868"
  },
  {
    "student_name": "Milan paul",
    "father_name": "Paul antony",
    "email": "msinc1000@gmail.com",
    "class_applying": "Class 11",
    "father_phone": "9947921520",
    "mother_phone": "9447796951",
    "dob": "21/10/2009",
    "gender": "Male",
    "address": "CHENNAI,south chittoor,divine nagar,9th cross,koduvelil house",
    "message": ".",
    "counsellor_remarks": "REGISTERED ",
    "next_followup": "",
    "submitted_at": "25/03/2026",
    "phone": "9947921520",
    "school": "SBOA Annanagar",
    "status": "Pending",
    "score": 0,
    "source": "excel_import",
    "_id": "b24793f1",
    "created_at": "2026-05-03T18:27:28.910344"
  },
  {
    "student_name": "Advika S Nair",
    "father_name": "Sandeep M S",
    "email": "msinc1000@gmail.com",
    "class_applying": "Class 3",
    "father_phone": "9947921521",
    "mother_phone": "9447796952",
    "dob": "02/01/2018",
    "gender": "Female",
    "address": "First floor, Narayaneeyam house, south chittur, temple road, CHENNAI",
    "message": "I would like to seek admission to third standard for my daughter, 8 years old ",
    "counsellor_remarks": "Wrong enquiry ",
    "next_followup": "",
    "submitted_at": "30/03/2026",
    "phone": "9947921521",
    "school": "SBOA Annanagar",
    "status": "Pending",
    "score": 0,
    "source": "excel_import",
    "_id": "3afeb545",
    "created_at": "2026-05-03T18:27:28.941852"
  },
  {
    "student_name": "Haziqsidhiq",
    "father_name": "Aboobackersidhiq",
    "email": "msinc1000@gmail.com",
    "class_applying": "Pre-KG",
    "father_phone": "9947921522",
    "mother_phone": "9447796953",
    "dob": "10/27/0021",
    "gender": "Male",
    "address": "Srm road,cinex altia building,near pothyz",
    "message": "Kg admission enquiry ",
    "counsellor_remarks": "NO RESPONSE ",
    "next_followup": "",
    "submitted_at": "31/03/2026",
    "phone": "9947921522",
    "school": "SBOA Annanagar",
    "status": "Pending",
    "score": 0,
    "source": "excel_import",
    "_id": "d8b025d6",
    "created_at": "2026-05-03T18:27:28.971055"
  },
  {
    "student_name": "Haya anas",
    "father_name": "Mohammed Anas",
    "email": "msinc1000@gmail.com",
    "class_applying": "LKG",
    "father_phone": "9947921523",
    "mother_phone": "9447796954",
    "dob": "29/11/2021",
    "gender": "Male",
    "address": "Tata Tritvam , Marine drive , kochi",
    "message": "",
    "counsellor_remarks": "REGISTERED",
    "next_followup": "",
    "submitted_at": "31/03/2026",
    "phone": "9947921523",
    "school": "SBOA Annanagar",
    "status": "Pending",
    "score": 0,
    "source": "excel_import",
    "_id": "7a5c0991",
    "created_at": "2026-05-03T18:27:29.000294"
  },
  {
    "student_name": "Hafeez Muhammed KN ",
    "father_name": "Nissar KH ",
    "email": "msinc1000@gmail.com",
    "class_applying": "Class 11",
    "father_phone": "9947921524",
    "mother_phone": "9447796955",
    "dob": "19/06/2010",
    "gender": "Male",
    "address": "Kalappurakkal house,cheranelloor po",
    "message": "Is there computer science available",
    "counsellor_remarks": "Interested in Maths -Computer Science, given the fees details.\nNeeds time to discuss and will  update within a day or 2.",
    "next_followup": "",
    "submitted_at": "01/04/2026",
    "phone": "9947921524",
    "school": "SBOA Annanagar",
    "status": "Pending",
    "score": 0,
    "source": "excel_import",
    "_id": "b37f68dd",
    "created_at": "2026-05-03T18:27:29.033162"
  },
  {
    "student_name": "Shreya Sreejith ",
    "father_name": "Sreejith S Kumar",
    "email": "msinc1000@gmail.com",
    "class_applying": "Class 6",
    "father_phone": "9947921525",
    "mother_phone": "9447796956",
    "dob": "31/07/2015",
    "gender": "Female",
    "address": "CARA 5, CONVENT ROAD 1 , THOTTAKATTUKARA, ALUVA ",
    "message": "We may shift house, so no need to consider this address ",
    "counsellor_remarks": "REGISTERED ",
    "next_followup": "",
    "submitted_at": "02/04/2026",
    "phone": "9947921525",
    "school": "SBOA Annanagar",
    "status": "Pending",
    "score": 0,
    "source": "excel_import",
    "_id": "8d126b1d",
    "created_at": "2026-05-03T18:27:29.068242"
  },
  {
    "student_name": "Tanishka Sreejith ",
    "father_name": "Sreejith S Kumar ",
    "email": "msinc1000@gmail.com",
    "class_applying": "Class 1",
    "father_phone": "9947921526",
    "mother_phone": "9447796957",
    "dob": "23/07/2019",
    "gender": "Female",
    "address": "CARA 5, CONVENT ROAD 1, THOTTAKATTUKARA ALUVA ",
    "message": "We may shift house..Is there transportation facilities to Desom, Kunnumpuram?",
    "counsellor_remarks": "REGISTERED ",
    "next_followup": "",
    "submitted_at": "02/04/2026",
    "phone": "9947921526",
    "school": "SBOA Annanagar",
    "status": "Pending",
    "score": 0,
    "source": "excel_import",
    "_id": "68df320f",
    "created_at": "2026-05-03T18:27:29.099738"
  },
  {
    "student_name": "ACHINTYA A NAIR ",
    "father_name": "C.AJITHKUMAR",
    "email": "msinc1000@gmail.com",
    "class_applying": "Class 8",
    "father_phone": "9947921527",
    "mother_phone": "9447796958",
    "dob": "07/04/2013",
    "gender": "Male",
    "address": "C 2, Noveno Dreamflower Apartment,  CHANGAMPUZHA CROSS ROAD,  PONEKARA,  EDAPPALLY ",
    "message": "SBOAERK/103/2026-27",
    "counsellor_remarks": "Admission details conveyed. Website link also sent.",
    "next_followup": "",
    "submitted_at": "04/04/2026",
    "phone": "9947921527",
    "school": "SBOA Annanagar",
    "status": "Pending",
    "score": 0,
    "source": "excel_import",
    "_id": "14764254",
    "created_at": "2026-05-03T18:27:29.126401"
  },
  {
    "student_name": "Amaranth ",
    "father_name": "Ranjith PR",
    "email": "msinc1000@gmail.com",
    "class_applying": "Class 1",
    "father_phone": "9947921528",
    "mother_phone": "9447796959",
    "dob": "18/07/2020",
    "gender": "Male",
    "address": "Padikuzhakkal house",
    "message": "",
    "counsellor_remarks": "They are at Thrissur. They will visit the school when they come to kochi . Admission details sent.",
    "next_followup": "",
    "submitted_at": "06/04/2026",
    "phone": "9947921528",
    "school": "SBOA Annanagar",
    "status": "Pending",
    "score": 0,
    "source": "excel_import",
    "_id": "073031e5",
    "created_at": "2026-05-03T18:27:29.152759"
  },
  {
    "student_name": "Zia Mariyam Manu",
    "father_name": "Manu Chacko",
    "email": "msinc1000@gmail.com",
    "class_applying": "Pre-KG",
    "father_phone": "9947921529",
    "mother_phone": "9447796960",
    "dob": "18/12/2023",
    "gender": "Female",
    "address": "Kolanchery , conventvroad ,njaracakal",
    "message": "",
    "counsellor_remarks": "",
    "next_followup": "",
    "submitted_at": "06/04/2026",
    "phone": "9947921529",
    "school": "SBOA Annanagar",
    "status": "Pending",
    "score": 0,
    "source": "excel_import",
    "_id": "3e78a376",
    "created_at": "2026-05-03T18:27:29.179342"
  },
  {
    "student_name": "ADHIL BASIL ",
    "father_name": "BASIL GEORGE ",
    "email": "msinc1000@gmail.com",
    "class_applying": "Class 2",
    "father_phone": "9947921530",
    "mother_phone": "9447796961",
    "dob": "15/07/2019",
    "gender": "Male",
    "address": "Pallickakudiyil(h)), bysonvalley p. O, muttukadu ",
    "message": "",
    "counsellor_remarks": "website link shared",
    "next_followup": "",
    "submitted_at": "10/04/2026",
    "phone": "9947921530",
    "school": "SBOA Annanagar",
    "status": "Pending",
    "score": 0,
    "source": "excel_import",
    "_id": "67f7f629",
    "created_at": "2026-05-03T18:27:29.214848"
  }
]